[
    {"model": "equipos.temporada", "pk": 1, "fields": {"anio": 2023, "fecha_inicio": "2023-01-01T00:00:00Z", "fecha_fin": "2023-12-31T23:59:59Z"}}, {"model": "equipos.jugador", "pk": 1, "fields": {"nombre": "Jugador 1", "edad": 25, "habilidades": {"velocidad": 80, "fuerza": 75}, "moral": 85, "salario": "200000.00", "lesion": false, "equipo": 1, "nacionalidad": 1}}, {"model": "equipos.jugador", "pk": 2, "fields": {"nombre": "Jugador 2", "edad": 22, "habilidades": {"velocidad": 78, "fuerza": 80}, "moral": 88, "salario": "180000.00", "lesion": false, "equipo": 1, "nacionalidad": 2}}, {"model": "equipos.jugador", "pk": 3, "fields": {"nombre": "Jugador 3", "edad": 28, "habilidades": {"velocidad": 82, "fuerza": 70}, "moral": 90, "salario": "190000.00", "lesion": false, "equipo": 1, "nacionalidad": 3}}, {"model": "equipos.jugador", "pk": 4, "fields": {"nombre": "Jugador 4", "edad": 21, "habilidades": {"velocidad": 82, "fuerza": 70}, "moral": 90, "salario": "190000.00", "lesion": false, "equipo": 1, "nacionalidad": 3}}, {"model": "equipos.jugador", "pk": 5, "fields": {"nombre": "Jugador 5", "edad": 30, "habilidades": {"velocidad": 82, "fuerza": 70}, "moral": 90, "salario": "190000.00", "lesion": false, "equipo": 1, "nacionalidad": 3}}, {"model": "equipos.jugador", "pk": 6, "fields": {"nombre": "Jugador 6", "edad": 24, "habilidades": {"velocidad": 82, "fuerza": 70}, "moral": 90, "salario": "190000.00", "lesion": false, "equipo": 1, "nacionalidad": 3}},
    
    {"model": "equipos.jugador", "pk": 7, "fields": {"nombre": "Jugador 7", "edad": 27, "habilidades": {"velocidad": 82, "fuerza": 70}, "moral": 90, "salario": "190000.00", "lesion": false, "equipo": 1, "nacionalidad": 3}},
    {"model": "equipos.jugador", "pk": 8, "fields": {"nombre": "Jugador 8", "edad": 19, "habilidades": {"velocidad": 82, "fuerza": 70}, "moral": 90, "salario": "190000.00", "lesion": false, "equipo": 1, "nacionalidad": 2}},
    {"model": "equipos.jugador", "pk": 9, "fields": {"nombre": "Jugador 9", "edad": 23, "habilidades": {"velocidad": 82, "fuerza": 70}, "moral": 90, "salario": "190000.00", "lesion": false, "equipo": 1, "nacionalidad": 2}},
    {"model": "equipos.jugador", "pk": 10, "fields": {"nombre": "Jugador 10", "edad": 29, "habilidades": {"velocidad": 82, "fuerza": 70}, "moral": 90, "salario": "190000.00", "lesion": false, "equipo": 1, "nacionalidad": 3}},
    {"model": "equipos.jugador", "pk": 11, "fields": {"nombre": "Jugador 11", "edad": 20, "habilidades": {"velocidad": 82, "fuerza": 70}, "moral": 90, "salario": "190000.00", "lesion": false, "equipo": 1, "nacionalidad": 3}},
    {"model": "equipos.jugador", "pk": 12, "fields": {"nombre": "Jugador 12", "edad": 26, "habilidades": {"velocidad": 82, "fuerza": 70}, "moral": 90, "salario": "190000.00", "lesion": false, "equipo": 2, "nacionalidad": 1}},
    {"model": "equipos.jugador", "pk": 13, "fields": {"nombre": "Jugador 13", "edad": 31, "habilidades": {"velocidad": 82, "fuerza": 70}, "moral": 90, "salario": "190000.00", "lesion": false, "equipo": 2, "nacionalidad": 2}},
    {"model": "equipos.jugador", "pk": 14, "fields": {"nombre": "Jugador 14", "edad": 18, "habilidades": {"velocidad": 82, "fuerza": 70}, "moral": 90, "salario": "190000.00", "lesion": false, "equipo": 2, "nacionalidad": 2}},
    {"model": "equipos.jugador", "pk": 15, "fields": {"nombre": "Jugador 15", "edad": 25, "habilidades": {"velocidad": 82, "fuerza": 70}, "moral": 90, "salario": "190000.00", "lesion": false, "equipo": 2, "nacionalidad": 2}},
    {"model": "equipos.jugador", "pk": 16, "fields": {"nombre": "Jugador 16", "edad": 22, "habilidades": {"velocidad": 82, "fuerza": 70}, "moral": 90, "salario": "190000.00", "lesion": false, "equipo": 2, "nacionalidad": 3}},
    {"model": "equipos.jugador", "pk": 17, "fields": {"nombre": "Jugador 17", "edad": 28, "habilidades": {"velocidad": 82, "fuerza": 70}, "moral": 90, "salario": "190000.00", "lesion": false, "equipo": 2, "nacionalidad": 2}},
    {"model": "equipos.jugador", "pk": 18, "fields": {"nombre": "Jugador 18", "edad": 21, "habilidades": {"velocidad": 82, "fuerza": 70}, "moral": 90, "salario": "190000.00", "lesion": false, "equipo": 2, "nacionalidad": 2}},
    {"model": "equipos.jugador", "pk": 19, "fields": {"nombre": "Jugador 19", "edad": 30, "habilidades": {"velocidad": 82, "fuerza": 70}, "moral": 90, "salario": "190000.00", "lesion": false, "equipo": 2, "nacionalidad": 3}},
    {"model": "equipos.jugador", "pk": 20, "fields": {"nombre": "Jugador 20", "edad": 24, "habilidades": {"velocidad": 82, "fuerza": 70}, "moral": 90, "salario": "190000.00", "lesion": false, "equipo": 2, "nacionalidad": 3}},
    {"model": "equipos.jugador", "pk": 21, "fields": {"nombre": "Jugador 21", "edad": 27, "habilidades": {"velocidad": 82, "fuerza": 70}, "moral": 90, "salario": "190000.00", "lesion": false, "equipo": 2, "nacionalidad": 3}},
    {"model": "equipos.jugador", "pk": 22, "fields": {"nombre": "Jugador 22", "edad": 19, "habilidades": {"velocidad": 82, "fuerza": 70}, "moral": 90, "salario": "190000.00", "lesion": false, "equipo": 2, "nacionalidad": 3}},
    {"model": "equipos.jugador", "pk": 23, "fields": {"nombre": "Jugador 23", "edad": 23, "habilidades": {"velocidad": 82, "fuerza": 70}, "moral": 90, "salario": "190000.00", "lesion": false, "equipo": 3, "nacionalidad": 1}},
    {"model": "equipos.jugador", "pk": 24, "fields": {"nombre": "Jugador 24", "edad": 29, "habilidades": {"velocidad": 82, "fuerza": 70}, "moral": 90, "salario": "190000.00", "lesion": false, "equipo": 3, "nacionalidad": 2}},
    {"model": "equipos.jugador", "pk": 25, "fields": {"nombre": "Jugador 25", "edad": 20, "habilidades": {"velocidad": 82, "fuerza": 70}, "moral": 90, "salario": "190000.00", "lesion": false, "equipo": 3, "nacionalidad": 3}},
    {"model": "equipos.jugador", "pk": 26, "fields": {"nombre": "Jugador 26", "edad": 26, "habilidades": {"velocidad": 82, "fuerza": 70}, "moral": 90, "salario": "190000.00", "lesion": false, "equipo": 3, "nacionalidad": 3}},
    {"model": "equipos.jugador", "pk": 27, "fields": {"nombre": "Jugador 27", "edad": 31, "habilidades": {"velocidad": 82, "fuerza": 70}, "moral": 90, "salario": "190000.00", "lesion": false, "equipo": 3, "nacionalidad": 3}},
    {"model": "equipos.jugador", "pk": 28, "fields": {"nombre": "Jugador 28", "edad": 18, "habilidades": {"velocidad": 82, "fuerza": 70}, "moral": 90, "salario": "190000.00", "lesion": false, "equipo": 3, "nacionalidad": 3}},
    {"model": "equipos.jugador", "pk": 29, "fields": {"nombre": "Jugador 29", "edad": 25, "habilidades": {"velocidad": 82, "fuerza": 70}, "moral": 90, "salario": "190000.00", "lesion": false, "equipo": 3, "nacionalidad": 3}},
    {"model": "equipos.jugador", "pk": 30, "fields": {"nombre": "Jugador 30", "edad": 22, "habilidades": {"velocidad": 82, "fuerza": 70}, "moral": 90, "salario": "190000.00", "lesion": false, "equipo": 3, "nacionalidad": 3}},
    {"model": "equipos.jugador", "pk": 31, "fields": {"nombre": "Jugador 31", "edad": 28, "habilidades": {"velocidad": 82, "fuerza": 70}, "moral": 90, "salario": "190000.00", "lesion": false, "equipo": 3, "nacionalidad": 1}},
    {"model": "equipos.jugador", "pk": 32, "fields": {"nombre": "Jugador 32", "edad": 21, "habilidades": {"velocidad": 82, "fuerza": 70}, "moral": 90, "salario": "190000.00", "lesion": false, "equipo": 3, "nacionalidad": 2}},
    {"model": "equipos.jugador", "pk": 33, "fields": {"nombre": "Jugador 33", "edad": 30, "habilidades": {"velocidad": 82, "fuerza": 70}, "moral": 90, "salario": "190000.00", "lesion": false, "equipo": 3, "nacionalidad": 2}},
    {"model": "equipos.jugador", "pk": 34, "fields": {"nombre": "Jugador 34", "edad": 24, "habilidades": {"velocidad": 82, "fuerza": 70}, "moral": 90, "salario": "190000.00", "lesion": false, "equipo": 4, "nacionalidad": 3}},
    {"model": "equipos.jugador", "pk": 35, "fields": {"nombre": "Jugador 35", "edad": 19, "habilidades": {"velocidad": 82, "fuerza": 70}, "moral": 90, "salario": "190000.00", "lesion": false, "equipo": 4, "nacionalidad": 2}},
    {"model": "equipos.jugador", "pk": 36, "fields": {"nombre": "Jugador 36", "edad": 28, "habilidades": {"velocidad": 82, "fuerza": 70}, "moral": 90, "salario": "190000.00", "lesion": false, "equipo": 4, "nacionalidad": 2}},
    {"model": "equipos.jugador", "pk": 37, "fields": {"nombre": "Jugador 37", "edad": 21, "habilidades": {"velocidad": 82, "fuerza": 70}, "moral": 90, "salario": "190000.00", "lesion": false, "equipo": 4, "nacionalidad": 3}},
    {"model": "equipos.jugador", "pk": 38, "fields": {"nombre": "Jugador 38", "edad": 30, "habilidades": {"velocidad": 82, "fuerza": 70}, "moral": 90, "salario": "190000.00", "lesion": false, "equipo": 4, "nacionalidad": 2}},
    {"model": "equipos.jugador", "pk": 39, "fields": {"nombre": "Jugador 39", "edad": 23, "habilidades": {"velocidad": 82, "fuerza": 70}, "moral": 90, "salario": "190000.00", "lesion": false, "equipo": 4, "nacionalidad": 2}},
    {"model": "equipos.jugador", "pk": 40, "fields": {"nombre": "Jugador 40", "edad": 27, "habilidades": {"velocidad": 82, "fuerza": 70}, "moral": 90, "salario": "190000.00", "lesion": false, "equipo": 4, "nacionalidad": 2}},
    {"model": "equipos.jugador", "pk": 41, "fields": {"nombre": "Jugador 41", "edad": 22, "habilidades": {"velocidad": 82, "fuerza": 70}, "moral": 90, "salario": "190000.00", "lesion": false, "equipo": 4, "nacionalidad": 1}},
    {"model": "equipos.jugador", "pk": 42, "fields": {"nombre": "Jugador 42", "edad": 31, "habilidades": {"velocidad": 82, "fuerza": 70}, "moral": 90, "salario": "190000.00", "lesion": false, "equipo": 4, "nacionalidad": 2}},
    {"model": "equipos.jugador", "pk": 43, "fields": {"nombre": "Jugador 43", "edad": 20, "habilidades": {"velocidad": 82, "fuerza": 70}, "moral": 90, "salario": "190000.00", "lesion": false, "equipo": 4, "nacionalidad": 3}},
    {"model": "equipos.jugador", "pk": 44, "fields": {"nombre": "Jugador 44", "edad": 29, "habilidades": {"velocidad": 82, "fuerza": 70}, "moral": 90, "salario": "190000.00", "lesion": false, "equipo": 4, "nacionalidad": 3}},
    {"model": "equipos.jugador", "pk": 45, "fields": {"nombre": "Jugador 45", "edad": 18, "habilidades": {"velocidad": 82, "fuerza": 70}, "moral": 90, "salario": "190000.00", "lesion": false, "equipo": 5, "nacionalidad": 3}},
    {"model": "equipos.jugador", "pk": 46, "fields": {"nombre": "Jugador 46", "edad": 26, "habilidades": {"velocidad": 82, "fuerza": 70}, "moral": 90, "salario": "190000.00", "lesion": false, "equipo": 5, "nacionalidad": 3}},
    {"model": "equipos.jugador", "pk": 47, "fields": {"nombre": "Jugador 47", "edad": 25, "habilidades": {"velocidad": 82, "fuerza": 70}, "moral": 90, "salario": "190000.00", "lesion": false, "equipo": 5, "nacionalidad": 3}},
    {"model": "equipos.jugador", "pk": 48, "fields": {"nombre": "Jugador 48", "edad": 32, "habilidades": {"velocidad": 82, "fuerza": 70}, "moral": 90, "salario": "190000.00", "lesion": false, "equipo": 5, "nacionalidad": 3}},
    {"model": "equipos.jugador", "pk": 49, "fields": {"nombre": "Jugador 49", "edad": 24, "habilidades": {"velocidad": 82, "fuerza": 70}, "moral": 90, "salario": "190000.00", "lesion": false, "equipo": 5, "nacionalidad": 3}},
    {"model": "equipos.jugador", "pk": 50, "fields": {"nombre": "Jugador 50", "edad": 19, "habilidades": {"velocidad": 82, "fuerza": 70}, "moral": 90, "salario": "190000.00", "lesion": false, "equipo": 5, "nacionalidad": 3}},
    {"model": "equipos.jugador", "pk": 51, "fields": {"nombre": "Jugador 51", "edad": 28, "habilidades": {"velocidad": 82, "fuerza": 70}, "moral": 90, "salario": "190000.00", "lesion": false, "equipo": 5, "nacionalidad": 3}},
    {"model": "equipos.jugador", "pk": 52, "fields": {"nombre": "Jugador 52", "edad": 21, "habilidades": {"velocidad": 82, "fuerza": 70}, "moral": 90, "salario": "190000.00", "lesion": false, "equipo": 5, "nacionalidad": 3}},
    {"model": "equipos.jugador", "pk": 53, "fields": {"nombre": "Jugador 53", "edad": 30, "habilidades": {"velocidad": 82, "fuerza": 70}, "moral": 90, "salario": "190000.00", "lesion": false, "equipo": 5, "nacionalidad": 3}},
    {"model": "equipos.jugador", "pk": 54, "fields": {"nombre": "Jugador 54", "edad": 23, "habilidades": {"velocidad": 82, "fuerza": 70}, "moral": 90, "salario": "190000.00", "lesion": false, "equipo": 5, "nacionalidad": 3}},
    {"model": "equipos.jugador", "pk": 55, "fields": {"nombre": "Jugador 55", "edad": 27, "habilidades": {"velocidad": 82, "fuerza": 70}, "moral": 90, "salario": "190000.00", "lesion": false, "equipo": 5, "nacionalidad": 3}},
    {"model": "equipos.jugador", "pk": 56, "fields": {"nombre": "Jugador 56", "edad": 22, "habilidades": {"velocidad": 82, "fuerza": 70}, "moral": 90, "salario": "190000.00", "lesion": false, "equipo": 6, "nacionalidad": 3}},
    {"model": "equipos.jugador", "pk": 57, "fields": {"nombre": "Jugador 57", "edad": 31, "habilidades": {"velocidad": 82, "fuerza": 70}, "moral": 90, "salario": "190000.00", "lesion": false, "equipo": 6, "nacionalidad": 3}},
    {"model": "equipos.jugador", "pk": 58, "fields": {"nombre": "Jugador 58", "edad": 20, "habilidades": {"velocidad": 82, "fuerza": 70}, "moral": 90, "salario": "190000.00", "lesion": false, "equipo": 6, "nacionalidad": 3}},
    {"model": "equipos.jugador", "pk": 59, "fields": {"nombre": "Jugador 59", "edad": 29, "habilidades": {"velocidad": 82, "fuerza": 70}, "moral": 90, "salario": "190000.00", "lesion": false, "equipo": 6, "nacionalidad": 3}},
    {"model": "equipos.jugador", "pk": 60, "fields": {"nombre": "Jugador 60", "edad": 18, "habilidades": {"velocidad": 82, "fuerza": 70}, "moral": 90, "salario": "190000.00", "lesion": false, "equipo": 6, "nacionalidad": 3}},
    {"model": "equipos.jugador", "pk": 61, "fields": {"nombre": "Jugador 61", "edad": 26, "habilidades": {"velocidad": 82, "fuerza": 70}, "moral": 90, "salario": "190000.00", "lesion": false, "equipo": 6, "nacionalidad": 3}},
    {"model": "equipos.jugador", "pk": 62, "fields": {"nombre": "Jugador 62", "edad": 25, "habilidades": {"velocidad": 82, "fuerza": 70}, "moral": 90, "salario": "190000.00", "lesion": false, "equipo": 6, "nacionalidad": 3}},
    {"model": "equipos.jugador", "pk": 63, "fields": {"nombre": "Jugador 63", "edad": 32, "habilidades": {"velocidad": 82, "fuerza": 70}, "moral": 90, "salario": "190000.00", "lesion": false, "equipo": 6, "nacionalidad": 3}},
    {"model": "equipos.jugador", "pk": 64, "fields": {"nombre": "Jugador 64", "edad": 24, "habilidades": {"velocidad": 82, "fuerza": 70}, "moral": 90, "salario": "190000.00", "lesion": false, "equipo": 6, "nacionalidad": 3}},
    {"model": "equipos.jugador", "pk": 65, "fields": {"nombre": "Jugador 65", "edad": 19, "habilidades": {"velocidad": 82, "fuerza": 70}, "moral": 90, "salario": "190000.00", "lesion": false, "equipo": 6, "nacionalidad": 3}},
    {"model": "equipos.jugador", "pk": 66, "fields": {"nombre": "Jugador 66", "edad": 28, "habilidades": {"velocidad": 82, "fuerza": 70}, "moral": 90, "salario": "190000.00", "lesion": false, "equipo": 6, "nacionalidad": 3}},
    {"model": "equipos.jugador", "pk": 67, "fields": {"nombre": "Jugador 67", "edad": 21, "habilidades": {"velocidad": 82, "fuerza": 70}, "moral": 90, "salario": "190000.00", "lesion": false, "equipo": 7, "nacionalidad": 3}},
    {"model": "equipos.jugador", "pk": 68, "fields": {"nombre": "Jugador 68", "edad": 30, "habilidades": {"velocidad": 82, "fuerza": 70}, "moral": 90, "salario": "190000.00", "lesion": false, "equipo": 7, "nacionalidad": 3}},
    {"model": "equipos.jugador", "pk": 69, "fields": {"nombre": "Jugador 69", "edad": 23, "habilidades": {"velocidad": 82, "fuerza": 70}, "moral": 90, "salario": "190000.00", "lesion": false, "equipo": 7, "nacionalidad": 3}},
    {"model": "equipos.jugador", "pk": 70, "fields": {"nombre": "Jugador 70", "edad": 27, "habilidades": {"velocidad": 82, "fuerza": 70}, "moral": 90, "salario": "190000.00", "lesion": false, "equipo": 7, "nacionalidad": 3}},
    {"model": "equipos.jugador", "pk": 71, "fields": {"nombre": "Jugador 71", "edad": 22, "habilidades": {"velocidad": 82, "fuerza": 70}, "moral": 90, "salario": "190000.00", "lesion": false, "equipo": 7, "nacionalidad": 3}},
    {"model": "equipos.jugador", "pk": 72, "fields": {"nombre": "Jugador 72", "edad": 31, "habilidades": {"velocidad": 82, "fuerza": 70}, "moral": 90, "salario": "190000.00", "lesion": false, "equipo": 7, "nacionalidad": 3}},
    {"model": "equipos.jugador", "pk": 73, "fields": {"nombre": "Jugador 73", "edad": 21, "habilidades": {"velocidad": 82, "fuerza": 70}, "moral": 90, "salario": "190000.00", "lesion": false, "equipo": 7, "nacionalidad": 3}},
    {"model": "equipos.jugador", "pk": 74, "fields": {"nombre": "Jugador 74", "edad": 25, "habilidades": {"velocidad": 82, "fuerza": 70}, "moral": 90, "salario": "190000.00", "lesion": false, "equipo": 7, "nacionalidad": 3}},
    {"model": "equipos.jugador", "pk": 75, "fields": {"nombre": "Jugador 75", "edad": 19, "habilidades": {"velocidad": 82, "fuerza": 70}, "moral": 90, "salario": "190000.00", "lesion": false, "equipo": 7, "nacionalidad": 3}},
    {"model": "equipos.jugador", "pk": 76, "fields": {"nombre": "Jugador 76", "edad": 28, "habilidades": {"velocidad": 82, "fuerza": 70}, "moral": 90, "salario": "190000.00", "lesion": false, "equipo": 7, "nacionalidad": 3}},
    {"model": "equipos.jugador", "pk": 77, "fields": {"nombre": "Jugador 77", "edad": 23, "habilidades": {"velocidad": 82, "fuerza": 70}, "moral": 90, "salario": "190000.00", "lesion": false, "equipo": 7, "nacionalidad": 3}},
    {"model": "equipos.jugador", "pk": 78, "fields": {"nombre": "Jugador 78", "edad": 24, "habilidades": {"velocidad": 85, "fuerza": 80}, "moral": 95, "salario": "210000.00", "lesion": false, "equipo": 8, "nacionalidad": 1}},
    {"model": "equipos.jugador", "pk": 79, "fields": {"nombre": "Jugador 79", "edad": 30, "habilidades": {"velocidad": 86, "fuerza": 81}, "moral": 96, "salario": "215000.00", "lesion": false, "equipo": 8, "nacionalidad": 2}},
    {"model": "equipos.jugador", "pk": 80, "fields": {"nombre": "Jugador 80", "edad": 22, "habilidades": {"velocidad": 87, "fuerza": 82}, "moral": 97, "salario": "220000.00", "lesion": false, "equipo": 8, "nacionalidad": 3}},
    {"model": "equipos.jugador", "pk": 81, "fields": {"nombre": "Jugador 81", "edad": 27, "habilidades": {"velocidad": 88, "fuerza": 83}, "moral": 98, "salario": "225000.00", "lesion": false, "equipo": 8, "nacionalidad": 1}},
    {"model": "equipos.jugador", "pk": 82, "fields": {"nombre": "Jugador 82", "edad": 20, "habilidades": {"velocidad": 89, "fuerza": 84}, "moral": 99, "salario": "230000.00", "lesion": false, "equipo": 8, "nacionalidad": 2}},
    {"model": "equipos.jugador", "pk": 83, "fields": {"nombre": "Jugador 83", "edad": 29, "habilidades": {"velocidad": 90, "fuerza": 85}, "moral": 100, "salario": "235000.00", "lesion": false, "equipo": 8, "nacionalidad": 3}},
    {"model": "equipos.jugador", "pk": 84, "fields": {"nombre": "Jugador 84", "edad": 18, "habilidades": {"velocidad": 91, "fuerza": 86}, "moral": 101, "salario": "240000.00", "lesion": false, "equipo": 8, "nacionalidad": 1}},
    {"model": "equipos.jugador", "pk": 85, "fields": {"nombre": "Jugador 85", "edad": 32, "habilidades": {"velocidad": 92, "fuerza": 87}, "moral": 102, "salario": "245000.00", "lesion": false, "equipo": 8, "nacionalidad": 2}},
    {"model": "equipos.jugador", "pk": 86, "fields": {"nombre": "Jugador 86", "edad": 26, "habilidades": {"velocidad": 93, "fuerza": 88}, "moral": 103, "salario": "250000.00", "lesion": false, "equipo": 8, "nacionalidad": 3}},
    {"model": "equipos.jugador", "pk": 87, "fields": {"nombre": "Jugador 87", "edad": 31, "habilidades": {"velocidad": 94, "fuerza": 89}, "moral": 104, "salario": "255000.00", "lesion": false, "equipo": 8, "nacionalidad": 1}},
    {"model": "equipos.jugador", "pk": 88, "fields": {"nombre": "Jugador 88", "edad": 19, "habilidades": {"velocidad": 95, "fuerza": 90}, "moral": 105, "salario": "260000.00", "lesion": false, "equipo": 8, "nacionalidad": 2}},

    {"model": "equipos.jugador", "pk": 80, "fields": {"nombre": "Suplente 1", "edad": 21, "habilidades": {"velocidad": 70, "fuerza": 65}, "moral": 80, "salario": "150000.00", "lesion": false, "equipo": 1, "nacionalidad": 1}},
    {"model": "equipos.jugador", "pk": 81, "fields": {"nombre": "Suplente 2", "edad": 25, "habilidades": {"velocidad": 72, "fuerza": 68}, "moral": 82, "salario": "155000.00", "lesion": false, "equipo": 1, "nacionalidad": 2}},
    {"model": "equipos.jugador", "pk": 82, "fields": {"nombre": "Suplente 3", "edad": 19, "habilidades": {"velocidad": 74, "fuerza": 70}, "moral": 84, "salario": "160000.00", "lesion": false, "equipo": 1, "nacionalidad": 3}},
    {"model": "equipos.jugador", "pk": 83, "fields": {"nombre": "Suplente 4", "edad": 28, "habilidades": {"velocidad": 76, "fuerza": 72}, "moral": 86, "salario": "165000.00", "lesion": false, "equipo": 1, "nacionalidad": 1}},
    {"model": "equipos.jugador", "pk": 84, "fields": {"nombre": "Suplente 5", "edad": 23, "habilidades": {"velocidad": 78, "fuerza": 74}, "moral": 88, "salario": "170000.00", "lesion": false, "equipo": 1, "nacionalidad": 2}},
    {"model": "equipos.jugador", "pk": 85, "fields": {"nombre": "Suplente 6", "edad": 24, "habilidades": {"velocidad": 80, "fuerza": 76}, "moral": 90, "salario": "175000.00", "lesion": false, "equipo": 1, "nacionalidad": 3}},

    {"model": "equipos.jugador", "pk": 86, "fields": {"nombre": "Suplente 1", "edad": 30, "habilidades": {"velocidad": 70, "fuerza": 65}, "moral": 80, "salario": "150000.00", "lesion": false, "equipo": 2, "nacionalidad": 1}},
    {"model": "equipos.jugador", "pk": 87, "fields": {"nombre": "Suplente 2", "edad": 22, "habilidades": {"velocidad": 72, "fuerza": 68}, "moral": 82, "salario": "155000.00", "lesion": false, "equipo": 2, "nacionalidad": 2}},
    {"model": "equipos.jugador", "pk": 88, "fields": {"nombre": "Suplente 3", "edad": 27, "habilidades": {"velocidad": 74, "fuerza": 70}, "moral": 84, "salario": "160000.00", "lesion": false, "equipo": 2, "nacionalidad": 3}},
    {"model": "equipos.jugador", "pk": 89, "fields": {"nombre": "Suplente 4", "edad": 20, "habilidades": {"velocidad": 76, "fuerza": 72}, "moral": 86, "salario": "165000.00", "lesion": false, "equipo": 2, "nacionalidad": 1}},
    {"model": "equipos.jugador", "pk": 90, "fields": {"nombre": "Suplente 5", "edad": 29, "habilidades": {"velocidad": 78, "fuerza": 74}, "moral": 88, "salario": "170000.00", "lesion": false, "equipo": 2, "nacionalidad": 2}},
    {"model": "equipos.jugador", "pk": 91, "fields": {"nombre": "Suplente 6", "edad": 18, "habilidades": {"velocidad": 80, "fuerza": 76}, "moral": 90, "salario": "175000.00", "lesion": false, "equipo": 2, "nacionalidad": 3}},

    {"model": "equipos.jugador", "pk": 92, "fields": {"nombre": "Suplente 1", "edad": 21, "habilidades": {"velocidad": 70, "fuerza": 65}, "moral": 80, "salario": "150000.00", "lesion": false, "equipo": 3, "nacionalidad": 1}},
    {"model": "equipos.jugador", "pk": 93, "fields": {"nombre": "Suplente 2", "edad": 25, "habilidades": {"velocidad": 72, "fuerza": 68}, "moral": 82, "salario": "155000.00", "lesion": false, "equipo": 3, "nacionalidad": 2}},
    {"model": "equipos.jugador", "pk": 94, "fields": {"nombre": "Suplente 3", "edad": 19, "habilidades": {"velocidad": 74, "fuerza": 70}, "moral": 84, "salario": "160000.00", "lesion": false, "equipo": 3, "nacionalidad": 3}},
    {"model": "equipos.jugador", "pk": 95, "fields": {"nombre": "Suplente 4", "edad": 28, "habilidades": {"velocidad": 76, "fuerza": 72}, "moral": 86, "salario": "165000.00", "lesion": false, "equipo": 3, "nacionalidad": 1}},
    {"model": "equipos.jugador", "pk": 96, "fields": {"nombre": "Suplente 5", "edad": 23, "habilidades": {"velocidad": 78, "fuerza": 74}, "moral": 88, "salario": "170000.00", "lesion": false, "equipo": 3, "nacionalidad": 2}},
    {"model": "equipos.jugador", "pk": 97, "fields": {"nombre": "Suplente 6", "edad": 24, "habilidades": {"velocidad": 80, "fuerza": 76}, "moral": 90, "salario": "175000.00", "lesion": false, "equipo": 3, "nacionalidad": 3}},

    {"model": "equipos.jugador", "pk": 98, "fields": {"nombre": "Suplente 1", "edad": 30, "habilidades": {"velocidad": 70, "fuerza": 65}, "moral": 80, "salario": "150000.00", "lesion": false, "equipo": 4, "nacionalidad": 1}},
    {"model": "equipos.jugador", "pk": 99, "fields": {"nombre": "Suplente 2", "edad": 22, "habilidades": {"velocidad": 72, "fuerza": 68}, "moral": 82, "salario": "155000.00", "lesion": false, "equipo": 4, "nacionalidad": 2}},
    {"model": "equipos.jugador", "pk": 100, "fields": {"nombre": "Suplente 3", "edad": 27, "habilidades": {"velocidad": 74, "fuerza": 70}, "moral": 84, "salario": "160000.00", "lesion": false, "equipo": 4, "nacionalidad": 3}},
    {"model": "equipos.jugador", "pk": 101, "fields": {"nombre": "Suplente 4", "edad": 20, "habilidades": {"velocidad": 76, "fuerza": 72}, "moral": 86, "salario": "165000.00", "lesion": false, "equipo": 4, "nacionalidad": 1}},
    {"model": "equipos.jugador", "pk": 102, "fields": {"nombre": "Suplente 5", "edad": 29, "habilidades": {"velocidad": 78, "fuerza": 74}, "moral": 88, "salario": "170000.00", "lesion": false, "equipo": 4, "nacionalidad": 2}},
    {"model": "equipos.jugador", "pk": 103, "fields": {"nombre": "Suplente 6", "edad": 18, "habilidades": {"velocidad": 80, "fuerza": 76}, "moral": 90, "salario": "175000.00", "lesion": false, "equipo": 4, "nacionalidad": 3}},

    {"model": "equipos.jugador", "pk": 104, "fields": {"nombre": "Suplente 1", "edad": 26, "habilidades": {"velocidad": 70, "fuerza": 65}, "moral": 80, "salario": "150000.00", "lesion": false, "equipo": 5, "nacionalidad": 1}},
    {"model": "equipos.jugador", "pk": 105, "fields": {"nombre": "Suplente 2", "edad": 25, "habilidades": {"velocidad": 72, "fuerza": 68}, "moral": 82, "salario": "155000.00", "lesion": false, "equipo": 5, "nacionalidad": 2}},
    {"model": "equipos.jugador", "pk": 106, "fields": {"nombre": "Suplente 3", "edad": 19, "habilidades": {"velocidad": 74, "fuerza": 70}, "moral": 84, "salario": "160000.00", "lesion": false, "equipo": 5, "nacionalidad": 3}},
    {"model": "equipos.jugador", "pk": 107, "fields": {"nombre": "Suplente 4", "edad": 28, "habilidades": {"velocidad": 76, "fuerza": 72}, "moral": 86, "salario": "165000.00", "lesion": false, "equipo": 5, "nacionalidad": 1}},
    {"model": "equipos.jugador", "pk": 108, "fields": {"nombre": "Suplente 5", "edad": 23, "habilidades": {"velocidad": 78, "fuerza": 74}, "moral": 88, "salario": "170000.00", "lesion": false, "equipo": 5, "nacionalidad": 2}},
    {"model": "equipos.jugador", "pk": 109, "fields": {"nombre": "Suplente 6", "edad": 24, "habilidades": {"velocidad": 80, "fuerza": 76}, "moral": 90, "salario": "175000.00", "lesion": false, "equipo": 5, "nacionalidad": 3}},

    {"model": "equipos.jugador", "pk": 110, "fields": {"nombre": "Suplente 1", "edad": 30, "habilidades": {"velocidad": 70, "fuerza": 65}, "moral": 80, "salario": "150000.00", "lesion": false, "equipo": 6, "nacionalidad": 1}},
    {"model": "equipos.jugador", "pk": 111, "fields": {"nombre": "Suplente 2", "edad": 22, "habilidades": {"velocidad": 72, "fuerza": 68}, "moral": 82, "salario": "155000.00", "lesion": false, "equipo": 6, "nacionalidad": 2}},
    {"model": "equipos.jugador", "pk": 112, "fields": {"nombre": "Suplente 3", "edad": 27, "habilidades": {"velocidad": 74, "fuerza": 70}, "moral": 84, "salario": "160000.00", "lesion": false, "equipo": 6, "nacionalidad": 3}},
    {"model": "equipos.jugador", "pk": 113, "fields": {"nombre": "Suplente 4", "edad": 20, "habilidades": {"velocidad": 76, "fuerza": 72}, "moral": 86, "salario": "165000.00", "lesion": false, "equipo": 6, "nacionalidad": 1}},
    {"model": "equipos.jugador", "pk": 114, "fields": {"nombre": "Suplente 5", "edad": 29, "habilidades": {"velocidad": 78, "fuerza": 74}, "moral": 88, "salario": "170000.00", "lesion": false, "equipo": 6, "nacionalidad": 2}},
    {"model": "equipos.jugador", "pk": 115, "fields": {"nombre": "Suplente 6", "edad": 18, "habilidades": {"velocidad": 80, "fuerza": 76}, "moral": 90, "salario": "175000.00", "lesion": false, "equipo": 6, "nacionalidad": 3}},

    {"model": "equipos.jugador", "pk": 116, "fields": {"nombre": "Suplente 1", "edad": 26, "habilidades": {"velocidad": 70, "fuerza": 65}, "moral": 80, "salario": "150000.00", "lesion": false, "equipo": 7, "nacionalidad": 1}},
    {"model": "equipos.jugador", "pk": 117, "fields": {"nombre": "Suplente 2", "edad": 25, "habilidades": {"velocidad": 72, "fuerza": 68}, "moral": 82, "salario": "155000.00", "lesion": false, "equipo": 7, "nacionalidad": 2}},
    {"model": "equipos.jugador", "pk": 118, "fields": {"nombre": "Suplente 3", "edad": 19, "habilidades": {"velocidad": 74, "fuerza": 70}, "moral": 84, "salario": "160000.00", "lesion": false, "equipo": 7, "nacionalidad": 3}},
    {"model": "equipos.jugador", "pk": 119, "fields": {"nombre": "Suplente 4", "edad": 28, "habilidades": {"velocidad": 76, "fuerza": 72}, "moral": 86, "salario": "165000.00", "lesion": false, "equipo": 7, "nacionalidad": 1}},
    {"model": "equipos.jugador", "pk": 120, "fields": {"nombre": "Suplente 5", "edad": 23, "habilidades": {"velocidad": 78, "fuerza": 74}, "moral": 88, "salario": "170000.00", "lesion": false, "equipo": 7, "nacionalidad": 2}},
    {"model": "equipos.jugador", "pk": 121, "fields": {"nombre": "Suplente 6", "edad": 24, "habilidades": {"velocidad": 80, "fuerza": 76}, "moral": 90, "salario": "175000.00", "lesion": false, "equipo": 7, "nacionalidad": 3}},

    {"model": "equipos.jugador", "pk": 122, "fields": {"nombre": "Suplente 1", "edad": 30, "habilidades": {"velocidad": 70, "fuerza": 65}, "moral": 80, "salario": "150000.00", "lesion": false, "equipo": 8, "nacionalidad": 1}},
    {"model": "equipos.jugador", "pk": 123, "fields": {"nombre": "Suplente 2", "edad": 22, "habilidades": {"velocidad": 72, "fuerza": 68}, "moral": 82, "salario": "155000.00", "lesion": false, "equipo": 8, "nacionalidad": 2}},
    {"model": "equipos.jugador", "pk": 124, "fields": {"nombre": "Suplente 3", "edad": 27, "habilidades": {"velocidad": 74, "fuerza": 70}, "moral": 84, "salario": "160000.00", "lesion": false, "equipo": 8, "nacionalidad": 3}},
    {"model": "equipos.jugador", "pk": 125, "fields": {"nombre": "Suplente 4", "edad": 20, "habilidades": {"velocidad": 76, "fuerza": 72}, "moral": 86, "salario": "165000.00", "lesion": false, "equipo": 8, "nacionalidad": 1}},
    {"model": "equipos.jugador", "pk": 126, "fields": {"nombre": "Suplente 5", "edad": 29, "habilidades": {"velocidad": 78, "fuerza": 74}, "moral": 88, "salario": "170000.00", "lesion": false, "equipo": 8, "nacionalidad": 2}},
    {"model": "equipos.jugador", "pk": 127, "fields": {"nombre": "Suplente 6", "edad": 18, "habilidades": {"velocidad": 80, "fuerza": 76}, "moral": 90, "salario": "175000.00", "lesion": false, "equipo": 8, "nacionalidad": 3}},

    {"model": "competiciones.competencia", "pk": 1, "fields": {"nombre": "Liga Local 2024", "tipo": "Liga Local", "temporada": 1, "equipos": [1, 2, 3, 4, 5, 6, 7, 8], "nacionalidad": 1, "fecha_inicio": "2024-12-17", "fecha_fin": "2025-12-31"}}

]
